{
    "name": "req-115202",
    "schemaVersion": "1.0",
    "tasks": [
        {
            "name": "req-115202-255200417_0",
            "flopsAmount": 1350000000.0,
            "machine": "bus_stop_3",
            "parents": []
        },
        {
            "name": "req-115202-255200372_0",
            "flopsAmount": 1350000000.0,
            "machine": "bus_stop_16",
            "parents": []
        },
        {
            "name": "req-115202-236868307_0",
            "flopsAmount": 1350000000.0,
            "machine": "bus_stop_16",
            "parents": []
        },
        {
            "name": "req-115202-236864890_1",
            "flopsAmount": 1350000000.0,
            "machine": "bus_stop_16",
            "parents": [
                "req-115202-255200417_0",
                "req-115202-255200372_0"
            ]
        },
        {
            "name": "req-115202-4414627711_1",
            "flopsAmount": 1350000000.0,
            "machine": "bus_stop_1",
            "parents": [
                "req-115202-236868307_0"
            ]
        },
        {
            "name": "req-115202-236868307_2",
            "flopsAmount": 1350000000.0,
            "machine": "bus_stop_16",
            "parents": [
                "req-115202-236864890_1",
                "req-115202-4414627711_1"
            ]
        },
        {
            "name": "req-115202-4414627711_3",
            "flopsAmount": 1350000000.0,
            "machine": "bus_stop_1",
            "parents": [
                "req-115202-236868307_2"
            ]
        }
    ]
}